{"pageProps":{"species":{"gen":4,"id":445,"name":"garchomp","evoStageLength":3,"evolvesFrom":444,"evolvesTo":[],"isFirstStage":false,"isLastStage":true,"pokemons":[["garchomp",[16,5]],["garchomp-mega",[16,5]]],"descriptions":["Garchomp is fast both underground and above. It can bring down prey and return to its den before its body has chilled from being outside.","Garchomp makes its home in volcanic mountains. It flies through the sky as fast as a jet airplane, hunting down as much prey as it can.","It can fly at speeds rivaling jet planes. It dives into flocks of bird Pokémon and gulps the entire flock down whole.","It flies at speeds equal to a jet fighter plane. It never allows its prey to escape.","It is said that when one runs at high speed, its wings create blades of wind that can fell nearby trees."],"habitat":null,"genderRate":4,"captureRate":45,"hatchCounter":40,"growthRateId":1,"baseHappiness":50,"eggGroupIds":[1,14],"isBaby":false,"isLegendary":false,"isMythical":false,"hasMega":true,"hasGmax":false,"pokemon":{"id":10058,"name":"garchomp-mega","types":[16,5],"height":19,"weight":950,"formName":"mega","stats":{"total":700,"hp":108,"atk":170,"def":115,"spAtk":120,"spDef":95,"spd":92},"minMaxStats":{"hp":[326,420],"atk":[310,482],"def":[211,361],"spAtk":[220,372],"spDef":[175,317],"spd":[170,311]},"evs":[["atk",3]],"baseExp":315,"abilities":[{"name":"sand-force","isHidden":false,"effect":"Strengthens rock, ground, and steel moves to 1.3× their power during a sandstorm.  Protects against sandstorm damage."}]}},"evolutions":[{"gen":4,"id":443,"name":"gible","evolvesFrom":null,"evolvesTo":[444],"pokemons":[{"id":443,"name":"gible","types":["dragon","ground"],"evolution":null}]},{"gen":4,"id":444,"name":"gabite","evolvesFrom":443,"evolvesTo":[445],"pokemons":[{"id":444,"name":"gabite","types":["dragon","ground"],"evolution":{"trigger":"level-up","lv":24}}]},{"gen":4,"id":445,"name":"garchomp","evolvesFrom":444,"evolvesTo":[],"pokemons":[{"id":445,"name":"garchomp","types":["dragon","ground"],"evolution":{"trigger":"level-up","lv":48}},{"id":10058,"name":"garchomp-mega","types":["dragon","ground"],"evolution":null}]}]},"__N_SSG":true}