{"pageProps":{"species":{"gen":8,"id":890,"name":"eternatus","evoStageLength":1,"evolvesFrom":null,"evolvesTo":[],"isFirstStage":false,"isLastStage":false,"pokemons":[["eternatus",[4,16]],["eternatus-eternamax",[4,16]]],"descriptions":["It was inside a meteorite that fell 20,000 years ago. There seems to be a connection between this Pokémon and the Dynamax phenomenon.","The core on its chest absorbs energy emanating from the lands of the Galar region. This energy is what allows Eternatus to stay active."],"habitat":null,"genderRate":-1,"captureRate":255,"hatchCounter":120,"growthRateId":1,"baseHappiness":0,"eggGroupIds":[15],"isBaby":false,"isLegendary":true,"isMythical":false,"hasMega":false,"hasGmax":false,"pokemon":{"id":10190,"name":"eternatus-eternamax","types":[4,16],"height":1000,"weight":0,"formName":"eternamax","stats":{"total":1125,"hp":255,"atk":115,"def":250,"spAtk":125,"spDef":250,"spd":130},"minMaxStats":{"hp":[620,714],"atk":[211,361],"def":[454,658],"spAtk":[229,383],"spDef":[454,658],"spd":[238,394]},"evs":[["hp",3]],"baseExp":563,"abilities":[{"name":"pressure","isHidden":false,"effect":"Increases the PP cost of moves targetting the Pokémon by one."}]}},"evolutions":[]},"__N_SSG":true}