{"pageProps":{"species":{"gen":4,"id":479,"name":"rotom","evoStageLength":1,"evolvesFrom":null,"evolvesTo":[],"isFirstStage":false,"isLastStage":false,"pokemons":[["rotom",[13,8]],["rotom-heat",[13,10]],["rotom-wash",[13,11]],["rotom-frost",[13,15]],["rotom-fan",[13,3]],["rotom-mow",[13,12]]],"descriptions":["Its body is composed of plasma. It is known to infiltrate electronic devices and wreak havoc.","Its electric-like body can enter some kinds of machines and take control in order to make mischief.","One boy’s invention led to the development of many different machines that take advantage of Rotom’s unique capabilities.","Research continues on this Pokémon, which could be the power source of a unique motor.","This bizarre Pokémon appears to be a will-o'-the-wisp powered by electricity. Be wary, as Rotom is both smart and mischievous."],"habitat":null,"genderRate":-1,"captureRate":45,"hatchCounter":20,"growthRateId":2,"baseHappiness":50,"eggGroupIds":[11],"isBaby":false,"isLegendary":false,"isMythical":false,"hasMega":false,"hasGmax":false,"pokemon":{"id":10011,"name":"rotom-fan","types":[13,3],"height":3,"weight":3,"formName":"fan","stats":{"total":520,"hp":50,"atk":65,"def":107,"spAtk":105,"spDef":107,"spd":86},"minMaxStats":{"hp":[210,304],"atk":[121,251],"def":[197,344],"spAtk":[193,339],"spDef":[197,344],"spd":[159,298]},"evs":[["spAtk",1],["spd",1]],"baseExp":182,"abilities":[{"name":"levitate","isHidden":false,"effect":"Evades ground moves."}]}},"evolutions":[]},"__N_SSG":true}