{"pageProps":{"species":{"gen":5,"id":522,"name":"blitzle","evoStageLength":2,"evolvesFrom":null,"evolvesTo":[523],"isFirstStage":true,"isLastStage":false,"pokemons":[["blitzle",[13]]],"descriptions":["Its mane shines when it discharges electricity. They use the frequency and rhythm of these flashes to communicate.","When thunderclouds cover the sky, it will appear. It can catch lightning with its mane and store the electricity."],"habitat":null,"genderRate":4,"captureRate":190,"hatchCounter":20,"growthRateId":2,"baseHappiness":70,"eggGroupIds":[5],"isBaby":false,"isLegendary":false,"isMythical":false,"hasMega":false,"hasGmax":false,"pokemon":{"id":522,"name":"blitzle","types":[13],"height":8,"weight":298,"formName":"","stats":{"total":295,"hp":45,"atk":60,"def":32,"spAtk":50,"spDef":32,"spd":76},"minMaxStats":{"hp":[200,294],"atk":[112,240],"def":[62,179],"spAtk":[94,218],"spDef":[62,179],"spd":[141,276]},"evs":[["spd",1]],"baseExp":59,"abilities":[{"name":"lightning-rod","isHidden":false,"effect":"Redirects single-target electric moves to this Pokémon where possible.  Absorbs Electric moves, raising Special Attack one stage."},{"name":"motor-drive","isHidden":false,"effect":"Absorbs electric moves, raising Speed one stage."},{"name":"sap-sipper","isHidden":true,"effect":"Absorbs grass moves, raising Attack one stage."}]}},"evolutions":[{"gen":5,"id":522,"name":"blitzle","evolvesFrom":null,"evolvesTo":[523],"pokemons":[{"id":522,"name":"blitzle","types":["electric"],"evolution":null}]},{"gen":5,"id":523,"name":"zebstrika","evolvesFrom":522,"evolvesTo":[],"pokemons":[{"id":523,"name":"zebstrika","types":["electric"],"evolution":{"trigger":"level-up","lv":27}}]}]},"__N_SSG":true}