{"pageProps":{"species":{"gen":3,"id":286,"name":"breloom","evoStageLength":2,"evolvesFrom":285,"evolvesTo":[],"isFirstStage":false,"isLastStage":true,"pokemons":[["breloom",[12,2]]],"descriptions":["Breloom closes in on its foe with light and sprightly footwork, then throws punches with its stretchy arms. This Pokémon’s fighting technique puts boxers to shame.","It scatters poisonous spores and throws powerful punches while its foe is hampered by inhaled spores.","It scatters spores from holes in the cap on its head. It loves warm and humid climates. It feeds on trees and plants in fields and forests.","Its short arms stretch when it throws punches. Its technique is equal to that of pro boxers.","The seeds on its tail are made of toxic spores. It knocks out foes with quick, virtually invisible punches."],"habitat":"forest","genderRate":4,"captureRate":90,"hatchCounter":15,"growthRateId":6,"baseHappiness":70,"eggGroupIds":[6,7],"isBaby":false,"isLegendary":false,"isMythical":false,"hasMega":false,"hasGmax":false,"pokemon":{"id":286,"name":"breloom","types":[12,2],"height":12,"weight":392,"formName":"","stats":{"total":460,"hp":60,"atk":130,"def":80,"spAtk":60,"spDef":60,"spd":70},"minMaxStats":{"hp":[230,324],"atk":[238,394],"def":[148,284],"spAtk":[112,240],"spDef":[112,240],"spd":[130,262]},"evs":[["atk",2]],"baseExp":161,"abilities":[{"name":"effect-spore","isHidden":false,"effect":"Has a 30% chance of inflcting either paralysis, poison, or sleep on attacking Pokémon on contact."},{"name":"poison-heal","isHidden":false,"effect":"Heals for 1/8 max HP after each turn when poisoned in place of damage."},{"name":"technician","isHidden":true,"effect":"Strengthens moves of 60 base power or less to 1.5× their power."}]}},"evolutions":[{"gen":3,"id":285,"name":"shroomish","evolvesFrom":null,"evolvesTo":[286],"pokemons":[{"id":285,"name":"shroomish","types":["grass"],"evolution":null}]},{"gen":3,"id":286,"name":"breloom","evolvesFrom":285,"evolvesTo":[],"pokemons":[{"id":286,"name":"breloom","types":["grass","fighting"],"evolution":{"trigger":"level-up","lv":23}}]}]},"__N_SSG":true}