{"pageProps":{"species":{"gen":4,"id":421,"name":"cherrim","evoStageLength":2,"evolvesFrom":420,"evolvesTo":[],"isFirstStage":false,"isLastStage":true,"pokemons":[["cherrim",[12]]],"descriptions":["As a bud, it barely moves. It sits still, placidly waiting for sunlight to appear.","During times of strong sunlight, its bud blooms, its petals open fully, and it becomes very active.","If it senses strong sunlight, it opens its folded petals to absorb the sun’s rays with its whole body.","It blooms during times of strong sunlight. It tries to make up for everything it endured as a bud.","It is docile as a bud, but turns cheerful when it blooms. It folds back into a bud if sunlight wanes."],"habitat":null,"genderRate":4,"captureRate":75,"hatchCounter":20,"growthRateId":2,"baseHappiness":50,"eggGroupIds":[6,7],"isBaby":false,"isLegendary":false,"isMythical":false,"hasMega":false,"hasGmax":false,"pokemon":{"id":421,"name":"cherrim","types":[12],"height":5,"weight":93,"formName":"overcast","stats":{"total":450,"hp":70,"atk":60,"def":70,"spAtk":87,"spDef":78,"spd":85},"minMaxStats":{"hp":[250,344],"atk":[112,240],"def":[130,262],"spAtk":[161,300],"spDef":[144,280],"spd":[157,295]},"evs":[["spAtk",2]],"baseExp":158,"abilities":[{"name":"flower-gift","isHidden":false,"effect":"Increases friendly Pokémon's Attack and Special Defense to 1.5× during strong sunlight."}]}},"evolutions":[{"gen":4,"id":420,"name":"cherubi","evolvesFrom":null,"evolvesTo":[421],"pokemons":[{"id":420,"name":"cherubi","types":["grass"],"evolution":null}]},{"gen":4,"id":421,"name":"cherrim","evolvesFrom":420,"evolvesTo":[],"pokemons":[{"id":421,"name":"cherrim","types":["grass"],"evolution":{"trigger":"level-up","lv":25}}]}]},"__N_SSG":true}