{"pageProps":{"species":{"gen":8,"id":832,"name":"dubwool","evoStageLength":2,"evolvesFrom":831,"evolvesTo":[],"isFirstStage":false,"isLastStage":true,"pokemons":[["dubwool",[1]]],"descriptions":["Its majestic horns are meant only to impress the opposite gender. They never see use in battle.","Weave a carpet from its springy wool, and you end up with something closer to a trampoline. You’ll start to bounce the moment you set foot on it."],"habitat":null,"genderRate":4,"captureRate":127,"hatchCounter":15,"growthRateId":2,"baseHappiness":50,"eggGroupIds":[5],"isBaby":false,"isLegendary":false,"isMythical":false,"hasMega":false,"hasGmax":false,"pokemon":{"id":832,"name":"dubwool","types":[1],"height":13,"weight":430,"formName":"","stats":{"total":490,"hp":72,"atk":80,"def":100,"spAtk":60,"spDef":90,"spd":88},"minMaxStats":{"hp":[254,348],"atk":[148,284],"def":[184,328],"spAtk":[112,240],"spDef":[166,306],"spd":[162,302]},"evs":[["def",2]],"baseExp":172,"abilities":[{"name":"fluffy","isHidden":false,"effect":"Damage from contact moves is halved.  Damage from Fire moves is doubled."},{"name":"steadfast","isHidden":false,"effect":"Raises Speed one stage upon flinching."},{"name":"bulletproof","isHidden":true,"effect":"Protects against bullet, ball, and bomb-based moves."}]}},"evolutions":[{"gen":8,"id":831,"name":"wooloo","evolvesFrom":null,"evolvesTo":[832],"pokemons":[{"id":831,"name":"wooloo","types":["normal"],"evolution":null}]},{"gen":8,"id":832,"name":"dubwool","evolvesFrom":831,"evolvesTo":[],"pokemons":[{"id":832,"name":"dubwool","types":["normal"],"evolution":{"trigger":"level-up","lv":24}}]}]},"__N_SSG":true}