{"pageProps":{"species":{"gen":1,"id":124,"name":"jynx","evoStageLength":2,"evolvesFrom":238,"evolvesTo":[],"isFirstStage":false,"isLastStage":true,"pokemons":[["jynx",[15,14]]],"descriptions":["A JYNX sashays rhythmically as if it were dancing. Its motions are so bouncingly alluring, people seeing it are compelled to shake their hips without noticing.","Appears to move to a rhythm of its own, as if it were dancing. It wiggles its hips as it walks.","In certain parts of Galar, Jynx was once feared and worshiped as the Queen of Ice.","It has several different cry patterns, each of which seems to have its own meaning.","It rocks its body rhythmically. It appears to alter the rhythm depending on how it is feeling."],"habitat":"urban","genderRate":8,"captureRate":45,"hatchCounter":25,"growthRateId":2,"baseHappiness":50,"eggGroupIds":[8],"isBaby":false,"isLegendary":false,"isMythical":false,"hasMega":false,"hasGmax":false,"pokemon":{"id":124,"name":"jynx","types":[15,14],"height":14,"weight":406,"formName":"","stats":{"total":455,"hp":65,"atk":50,"def":35,"spAtk":115,"spDef":95,"spd":95},"minMaxStats":{"hp":[240,334],"atk":[94,218],"def":[67,185],"spAtk":[211,361],"spDef":[175,317],"spd":[175,317]},"evs":[["spAtk",2]],"baseExp":159,"abilities":[{"name":"oblivious","isHidden":false,"effect":"Prevents infatuation and protects against captivate."},{"name":"forewarn","isHidden":false,"effect":"Reveals the opponents' strongest move upon entering battle."},{"name":"dry-skin","isHidden":true,"effect":"Causes 1/8 max HP in damage each turn during strong sunlight, but heals for 1/8 max HP during rain.  Increases damage from fire moves to 1.25×, but absorbs water moves, healing for 1/4 max HP."}]}},"evolutions":[{"gen":2,"id":238,"name":"smoochum","evolvesFrom":null,"evolvesTo":[124],"pokemons":[{"id":238,"name":"smoochum","types":["ice","psychic"],"evolution":null}]},{"gen":1,"id":124,"name":"jynx","evolvesFrom":238,"evolvesTo":[],"pokemons":[{"id":124,"name":"jynx","types":["ice","psychic"],"evolution":{"trigger":"level-up","lv":30}}]}]},"__N_SSG":true}