{"pageProps":{"species":{"gen":1,"id":86,"name":"seel","evoStageLength":2,"evolvesFrom":null,"evolvesTo":[87],"isFirstStage":true,"isLastStage":false,"pokemons":[["seel",[11]]],"descriptions":["Although it can't walk well on land, it is a graceful swimmer. It especially loves being in frigid seas.","A Pokémon that lives on icebergs. It swims in the sea using the point on its head to break up ice.","Covered with light blue fur, its hide is thick and tough. It is active in bitter cold of -40 degrees Fahrenheit.","In daytime, it is often found asleep on the seabed in shallow waters. Its nostrils close while it swims.","It has always been supposed that Seel live only in cold seas. Their having shown up in Alola is a mystery."],"habitat":"sea","genderRate":4,"captureRate":190,"hatchCounter":20,"growthRateId":2,"baseHappiness":70,"eggGroupIds":[2,5],"isBaby":false,"isLegendary":false,"isMythical":false,"hasMega":false,"hasGmax":false,"pokemon":{"id":86,"name":"seel","types":[11],"height":11,"weight":900,"formName":"","stats":{"total":325,"hp":65,"atk":45,"def":55,"spAtk":45,"spDef":70,"spd":45},"minMaxStats":{"hp":[240,334],"atk":[85,207],"def":[103,229],"spAtk":[85,207],"spDef":[130,262],"spd":[85,207]},"evs":[["spDef",1]],"baseExp":65,"abilities":[{"name":"thick-fat","isHidden":false,"effect":"Halves damage from fire and ice moves."},{"name":"hydration","isHidden":false,"effect":"Cures any major status ailment after each turn during rain."},{"name":"ice-body","isHidden":true,"effect":"Heals for 1/16 max HP after each turn during hail.  Protects against hail damage."}]}},"evolutions":[{"gen":1,"id":86,"name":"seel","evolvesFrom":null,"evolvesTo":[87],"pokemons":[{"id":86,"name":"seel","types":["water"],"evolution":null}]},{"gen":1,"id":87,"name":"dewgong","evolvesFrom":86,"evolvesTo":[],"pokemons":[{"id":87,"name":"dewgong","types":["water","ice"],"evolution":{"trigger":"level-up","lv":34}}]}]},"__N_SSG":true}