{"pageProps":{"species":{"gen":2,"id":191,"name":"sunkern","evoStageLength":2,"evolvesFrom":null,"evolvesTo":[192],"isFirstStage":true,"isLastStage":false,"pokemons":[["sunkern",[12]]],"descriptions":["It is very weak. Its only means of defense is to shake its leaves desperately at its attacker.","It lives by drinking only dewdrops from under the leaves of plants. It is said that it eats nothing else.","It may drop out of the sky suddenly. If attacked by a SPEAROW, it will violently shake its leaves.","It suddenly falls out of the sky in the morning. A year after a cold summer, their population explodes.","Sunkern tries to move as little as it possibly can. It does so because it tries to conserve all the nutrients it has stored in its body for its evolution. It will not eat a thing, subsisting only on morning dew."],"habitat":"grassland","genderRate":4,"captureRate":235,"hatchCounter":20,"growthRateId":4,"baseHappiness":70,"eggGroupIds":[7],"isBaby":false,"isLegendary":false,"isMythical":false,"hasMega":false,"hasGmax":false,"pokemon":{"id":191,"name":"sunkern","types":[12],"height":3,"weight":18,"formName":"","stats":{"total":180,"hp":30,"atk":30,"def":30,"spAtk":30,"spDef":30,"spd":30},"minMaxStats":{"hp":[170,264],"atk":[58,174],"def":[58,174],"spAtk":[58,174],"spDef":[58,174],"spd":[58,174]},"evs":[["spAtk",1]],"baseExp":36,"abilities":[{"name":"chlorophyll","isHidden":false,"effect":"Doubles Speed during strong sunlight."},{"name":"solar-power","isHidden":false,"effect":"Increases Special Attack to 1.5× but costs 1/8 max HP after each turn during strong sunlight."},{"name":"early-bird","isHidden":true,"effect":"Makes sleep pass twice as quickly."}]}},"evolutions":[{"gen":2,"id":191,"name":"sunkern","evolvesFrom":null,"evolvesTo":[192],"pokemons":[{"id":191,"name":"sunkern","types":["grass"],"evolution":null}]},{"gen":2,"id":192,"name":"sunflora","evolvesFrom":191,"evolvesTo":[],"pokemons":[{"id":192,"name":"sunflora","types":["grass"],"evolution":{"trigger":"use-item","lv":null,"item":"sun-stone"}}]}]},"__N_SSG":true}