{"pageProps":{"species":{"gen":2,"id":217,"name":"ursaring","evoStageLength":3,"evolvesFrom":216,"evolvesTo":[901],"isFirstStage":false,"isLastStage":false,"pokemons":[["ursaring",[1]]],"descriptions":["Although it has a large body, it is quite skilled at climbing trees. It eats and sleeps in the treetops.","Although it is a good climber, it prefers to snap stout trees with its forelegs and eat fallen BERRIES.","In forests, it is said that there are many streams and towering trees where an URSARING gathers food. It walks through its forest collecting food every day.","In its territory, it leaves scratches on trees that bear delicious berries or fruits.","When the cold season arrives in Hisui, this Pokémon will wander fields and mountains alike in search of its favorite berries. Ursaring's hunger during this time makes it a ferocious danger."],"habitat":"mountain","genderRate":4,"captureRate":60,"hatchCounter":20,"growthRateId":2,"baseHappiness":70,"eggGroupIds":[5],"isBaby":false,"isLegendary":false,"isMythical":false,"hasMega":false,"hasGmax":false,"pokemon":{"id":217,"name":"ursaring","types":[1],"height":18,"weight":1258,"formName":"","stats":{"total":500,"hp":90,"atk":130,"def":75,"spAtk":75,"spDef":75,"spd":55},"minMaxStats":{"hp":[290,384],"atk":[238,394],"def":[139,273],"spAtk":[139,273],"spDef":[139,273],"spd":[103,229]},"evs":[["atk",2]],"baseExp":175,"abilities":[{"name":"guts","isHidden":false,"effect":"Increases Attack to 1.5× with a major status ailment."},{"name":"quick-feet","isHidden":false,"effect":"Increases Speed to 1.5× with a major status ailment."},{"name":"unnerve","isHidden":true,"effect":"Prevents opposing Pokémon from eating held Berries."}]}},"evolutions":[{"gen":2,"id":216,"name":"teddiursa","evolvesFrom":null,"evolvesTo":[217],"pokemons":[{"id":216,"name":"teddiursa","types":["normal"],"evolution":null}]},{"gen":2,"id":217,"name":"ursaring","evolvesFrom":216,"evolvesTo":[901],"pokemons":[{"id":217,"name":"ursaring","types":["normal"],"evolution":{"trigger":"level-up","lv":30}}]},{"gen":8,"id":901,"name":"ursaluna","evolvesFrom":217,"evolvesTo":[],"pokemons":[{"id":901,"name":"ursaluna","types":["ground","normal"],"evolution":{"trigger":"use-item","lv":null,"item":"peat-block"}},{"id":10272,"name":"ursaluna-bloodmoon","types":["ground","normal"],"evolution":null}]}]},"__N_SSG":true}