{"pageProps":{"data":[{"id":"dp3-1","name":"Ampharos","supertype":"Pokémon","subtypes":["Stage 2"],"types":["Lightning"],"number":"1","artist":"Kouki Saitou","rarity":"Rare Holo","images":{"small":"https://images.pokemontcg.io/dp3/1.png","large":"https://images.pokemontcg.io/dp3/1_hires.png"}},{"id":"ex12-1","name":"Aerodactyl","supertype":"Pokémon","subtypes":["Stage 1"],"types":["Colorless"],"number":"1","artist":"Hajime Kusajima","rarity":"Rare Holo","images":{"small":"https://images.pokemontcg.io/ex12/1.png","large":"https://images.pokemontcg.io/ex12/1_hires.png"}},{"id":"mcd19-1","name":"Caterpie","supertype":"Pokémon","subtypes":["Basic"],"types":["Grass"],"number":"1","artist":"Sekio","images":{"small":"https://images.pokemontcg.io/mcd19/1.png","large":"https://images.pokemontcg.io/mcd19/1_hires.png"}},{"id":"ex7-1","name":"Azumarill","supertype":"Pokémon","subtypes":["Stage 1"],"types":["Water"],"number":"1","artist":"Sumiyoshi Kizuki","rarity":"Rare Holo","images":{"small":"https://images.pokemontcg.io/ex7/1.png","large":"https://images.pokemontcg.io/ex7/1_hires.png"}},{"id":"sm9-1","name":"Celebi & Venusaur-GX","supertype":"Pokémon","subtypes":["Basic","TAG TEAM","GX"],"types":["Grass"],"number":"1","artist":"Mitsuhiro Arita","rarity":"Rare Holo GX","images":{"small":"https://images.pokemontcg.io/sm9/1.png","large":"https://images.pokemontcg.io/sm9/1_hires.png"}},{"id":"pl1-2","name":"Blastoise","supertype":"Pokémon","subtypes":["Stage 2"],"types":["Water"],"number":"2","artist":"Kagemaru Himeno","rarity":"Rare Holo","images":{"small":"https://images.pokemontcg.io/pl1/2.png","large":"https://images.pokemontcg.io/pl1/2_hires.png"}},{"id":"ex3-2","name":"Altaria","supertype":"Pokémon","subtypes":["Stage 1"],"types":["Colorless"],"number":"2","artist":"Atsuko Nishida","rarity":"Rare Holo","images":{"small":"https://images.pokemontcg.io/ex3/2.png","large":"https://images.pokemontcg.io/ex3/2_hires.png"}},{"id":"sm9-2","name":"Weedle","supertype":"Pokémon","subtypes":["Basic"],"types":["Grass"],"number":"2","artist":"Shibuzoh.","rarity":"Common","images":{"small":"https://images.pokemontcg.io/sm9/2.png","large":"https://images.pokemontcg.io/sm9/2_hires.png"}},{"id":"mcd19-2","name":"Alolan Exeggutor","supertype":"Pokémon","subtypes":["Stage 1"],"types":["Grass"],"number":"2","artist":"Satoshi Shirai","images":{"small":"https://images.pokemontcg.io/mcd19/2.png","large":"https://images.pokemontcg.io/mcd19/2_hires.png"}},{"id":"xy5-2","name":"Kakuna","supertype":"Pokémon","subtypes":["Stage 1"],"types":["Grass"],"number":"2","artist":"Kagemaru Himeno","rarity":"Uncommon","images":{"small":"https://images.pokemontcg.io/xy5/2.png","large":"https://images.pokemontcg.io/xy5/2_hires.png"}},{"id":"sm12-1","name":"Venusaur & Snivy-GX","supertype":"Pokémon","subtypes":["Basic","TAG TEAM","GX"],"types":["Grass"],"number":"1","artist":"Mitsuhiro Arita","rarity":"Rare Holo GX","images":{"small":"https://images.pokemontcg.io/sm12/1.png","large":"https://images.pokemontcg.io/sm12/1_hires.png"}},{"id":"si1-1","name":"Mew","supertype":"Pokémon","subtypes":["Basic"],"types":["Psychic"],"number":"1","artist":"Keiko Fukuyama","images":{"small":"https://images.pokemontcg.io/si1/1.png","large":"https://images.pokemontcg.io/si1/1_hires.png"}},{"id":"sm3-1","name":"Caterpie","supertype":"Pokémon","subtypes":["Basic"],"types":["Grass"],"number":"1","artist":"Sekio","rarity":"Common","images":{"small":"https://images.pokemontcg.io/sm3/1.png","large":"https://images.pokemontcg.io/sm3/1_hires.png"}},{"id":"pop7-1","name":"Ampharos","supertype":"Pokémon","subtypes":["Stage 2"],"types":["Lightning"],"number":"1","artist":"Kouki Saitou","rarity":"Rare","images":{"small":"https://images.pokemontcg.io/pop7/1.png","large":"https://images.pokemontcg.io/pop7/1_hires.png"}},{"id":"bw1-2","name":"Snivy","supertype":"Pokémon","subtypes":["Basic"],"types":["Grass"],"number":"2","artist":"5ban Graphics","rarity":"Common","images":{"small":"https://images.pokemontcg.io/bw1/2.png","large":"https://images.pokemontcg.io/bw1/2_hires.png"}},{"id":"base4-3","name":"Chansey","supertype":"Pokémon","subtypes":["Basic"],"types":["Colorless"],"number":"3","artist":"Ken Sugimori","rarity":"Rare Holo","images":{"small":"https://images.pokemontcg.io/base4/3.png","large":"https://images.pokemontcg.io/base4/3_hires.png"}},{"id":"hgss4-3","name":"Celebi","supertype":"Pokémon","subtypes":["Basic"],"types":["Psychic"],"number":"3","artist":"Shin Nagasawa","rarity":"Rare Holo","images":{"small":"https://images.pokemontcg.io/hgss4/3.png","large":"https://images.pokemontcg.io/hgss4/3_hires.png"}},{"id":"ex7-3","name":"Dark Crobat","supertype":"Pokémon","subtypes":["Stage 2"],"types":["Grass","Darkness"],"number":"3","artist":"Kyoko Koizumi","rarity":"Rare Holo","images":{"small":"https://images.pokemontcg.io/ex7/3.png","large":"https://images.pokemontcg.io/ex7/3_hires.png"}},{"id":"swsh35-2","name":"Weedle","supertype":"Pokémon","subtypes":["Basic"],"types":["Grass"],"number":"2","artist":"Yuka Morii","rarity":"Common","images":{"small":"https://images.pokemontcg.io/swsh35/2.png","large":"https://images.pokemontcg.io/swsh35/2_hires.png"}},{"id":"xy2-3","name":"Butterfree","supertype":"Pokémon","subtypes":["Stage 2"],"types":["Grass"],"number":"3","artist":"sui","rarity":"Rare","images":{"small":"https://images.pokemontcg.io/xy2/3.png","large":"https://images.pokemontcg.io/xy2/3_hires.png"}},{"id":"sm9-3","name":"Weedle","supertype":"Pokémon","subtypes":["Basic"],"types":["Grass"],"number":"3","artist":"SATOSHI NAKAI","rarity":"Common","images":{"small":"https://images.pokemontcg.io/sm9/3.png","large":"https://images.pokemontcg.io/sm9/3_hires.png"}},{"id":"sm1-2","name":"Metapod","supertype":"Pokémon","subtypes":["Stage 1"],"types":["Grass"],"number":"2","artist":"Yuka Morii","rarity":"Uncommon","images":{"small":"https://images.pokemontcg.io/sm1/2.png","large":"https://images.pokemontcg.io/sm1/2_hires.png"}},{"id":"mcd19-3","name":"Magmar","supertype":"Pokémon","subtypes":["Basic"],"types":["Fire"],"number":"3","artist":"Yumi","images":{"small":"https://images.pokemontcg.io/mcd19/3.png","large":"https://images.pokemontcg.io/mcd19/3_hires.png"}},{"id":"dp3-3","name":"Charizard","supertype":"Pokémon","subtypes":["Stage 2"],"types":["Fire"],"number":"3","artist":"Daisuke Ito","rarity":"Rare Holo","images":{"small":"https://images.pokemontcg.io/dp3/3.png","large":"https://images.pokemontcg.io/dp3/3_hires.png"}}],"page":1,"pageSize":24,"count":24,"totalCount":17679},"__N_SSG":true}