{
  "data": [
    {
      "id": 669,
      "name": "flabebe",
      "gen": 6,
      "isLegendary": false,
      "isMythical": false,
      "isBaby": false,
      "captureRate": 225,
      "habitat": null,
      "pokemons": [
        {
          "id": 669,
          "name": "flabebe",
          "types": [
            "fairy"
          ]
        }
      ],
      "names": [
        "flabebe"
      ],
      "types": [
        "fairy"
      ]
    },
    {
      "id": 670,
      "name": "floette",
      "gen": 6,
      "isLegendary": false,
      "isMythical": false,
      "isBaby": false,
      "captureRate": 120,
      "habitat": null,
      "pokemons": [
        {
          "id": 670,
          "name": "floette",
          "types": [
            "fairy"
          ]
        },
        {
          "id": 10061,
          "name": "floette-eternal",
          "types": [
            "fairy"
          ]
        }
      ],
      "names": [
        "floette",
        "floette-eternal"
      ],
      "types": [
        "fairy"
      ]
    },
    {
      "id": 671,
      "name": "florges",
      "gen": 6,
      "isLegendary": false,
      "isMythical": false,
      "isBaby": false,
      "captureRate": 45,
      "habitat": null,
      "pokemons": [
        {
          "id": 671,
          "name": "florges",
          "types": [
            "fairy"
          ]
        }
      ],
      "names": [
        "florges"
      ],
      "types": [
        "fairy"
      ]
    },
    {
      "id": 682,
      "name": "spritzee",
      "gen": 6,
      "isLegendary": false,
      "isMythical": false,
      "isBaby": false,
      "captureRate": 200,
      "habitat": null,
      "pokemons": [
        {
          "id": 682,
          "name": "spritzee",
          "types": [
            "fairy"
          ]
        }
      ],
      "names": [
        "spritzee"
      ],
      "types": [
        "fairy"
      ]
    },
    {
      "id": 683,
      "name": "aromatisse",
      "gen": 6,
      "isLegendary": false,
      "isMythical": false,
      "isBaby": false,
      "captureRate": 140,
      "habitat": null,
      "pokemons": [
        {
          "id": 683,
          "name": "aromatisse",
          "types": [
            "fairy"
          ]
        }
      ],
      "names": [
        "aromatisse"
      ],
      "types": [
        "fairy"
      ]
    },
    {
      "id": 684,
      "name": "swirlix",
      "gen": 6,
      "isLegendary": false,
      "isMythical": false,
      "isBaby": false,
      "captureRate": 200,
      "habitat": null,
      "pokemons": [
        {
          "id": 684,
          "name": "swirlix",
          "types": [
            "fairy"
          ]
        }
      ],
      "names": [
        "swirlix"
      ],
      "types": [
        "fairy"
      ]
    },
    {
      "id": 685,
      "name": "slurpuff",
      "gen": 6,
      "isLegendary": false,
      "isMythical": false,
      "isBaby": false,
      "captureRate": 140,
      "habitat": null,
      "pokemons": [
        {
          "id": 685,
          "name": "slurpuff",
          "types": [
            "fairy"
          ]
        }
      ],
      "names": [
        "slurpuff"
      ],
      "types": [
        "fairy"
      ]
    },
    {
      "id": 700,
      "name": "sylveon",
      "gen": 6,
      "isLegendary": false,
      "isMythical": false,
      "isBaby": false,
      "captureRate": 45,
      "habitat": null,
      "pokemons": [
        {
          "id": 700,
          "name": "sylveon",
          "types": [
            "fairy"
          ]
        }
      ],
      "names": [
        "sylveon"
      ],
      "types": [
        "fairy"
      ]
    },
    {
      "id": 702,
      "name": "dedenne",
      "gen": 6,
      "isLegendary": false,
      "isMythical": false,
      "isBaby": false,
      "captureRate": 180,
      "habitat": null,
      "pokemons": [
        {
          "id": 702,
          "name": "dedenne",
          "types": [
            "electric",
            "fairy"
          ]
        }
      ],
      "names": [
        "dedenne"
      ],
      "types": [
        "electric",
        "fairy"
      ]
    },
    {
      "id": 703,
      "name": "carbink",
      "gen": 6,
      "isLegendary": false,
      "isMythical": false,
      "isBaby": false,
      "captureRate": 60,
      "habitat": null,
      "pokemons": [
        {
          "id": 703,
          "name": "carbink",
          "types": [
            "rock",
            "fairy"
          ]
        }
      ],
      "names": [
        "carbink"
      ],
      "types": [
        "rock",
        "fairy"
      ]
    },
    {
      "id": 707,
      "name": "klefki",
      "gen": 6,
      "isLegendary": false,
      "isMythical": false,
      "isBaby": false,
      "captureRate": 75,
      "habitat": null,
      "pokemons": [
        {
          "id": 707,
          "name": "klefki",
          "types": [
            "steel",
            "fairy"
          ]
        }
      ],
      "names": [
        "klefki"
      ],
      "types": [
        "steel",
        "fairy"
      ]
    },
    {
      "id": 716,
      "name": "xerneas",
      "gen": 6,
      "isLegendary": true,
      "isMythical": false,
      "isBaby": false,
      "captureRate": 45,
      "habitat": null,
      "pokemons": [
        {
          "id": 716,
          "name": "xerneas",
          "types": [
            "fairy"
          ]
        }
      ],
      "names": [
        "xerneas"
      ],
      "types": [
        "fairy"
      ]
    },
    {
      "id": 719,
      "name": "diancie",
      "gen": 6,
      "isLegendary": false,
      "isMythical": true,
      "isBaby": false,
      "captureRate": 3,
      "habitat": null,
      "pokemons": [
        {
          "id": 719,
          "name": "diancie",
          "types": [
            "rock",
            "fairy"
          ]
        },
        {
          "id": 10075,
          "name": "diancie-mega",
          "types": [
            "rock",
            "fairy"
          ]
        }
      ],
      "names": [
        "diancie",
        "diancie-mega"
      ],
      "types": [
        "rock",
        "fairy"
      ]
    }
  ],
  "page": 1,
  "nextPage": null
}